pydrying/__init__.py
pydrying/__main__.py
pydrying/__mesh__.py
pydrying/__version__.py
pydrying/dry.json
pydrying/dry.py
pydrying/moist_air.json
pydrying/moist_air.py
pydrying/test.py
pydrying-1.0.4.dist-info/LICENSE.txt
pydrying-1.0.4.dist-info/METADATA
pydrying-1.0.4.dist-info/WHEEL
pydrying-1.0.4.dist-info/top_level.txt
pydrying-1.0.4.dist-info/RECORD
