Metadata-Version: 2.1
Name: pydrying
Version: 1.0.4
Summary: Drying simulation of solid products
Home-page: https://pydrying.readthedocs.io/en/latest/
Author: Hedi ROMDHANA
Author-email: hedi.romdhana@agroparistech.fr
License: GPLv3
Keywords: drying simulation solid finte volume
Classifier: Development Status :: 3 - Alpha
Classifier: Intended Audience :: Developers
Classifier: Programming Language :: Python :: 3.4
Classifier: Programming Language :: Python :: 3.5
Classifier: Programming Language :: Python :: 3.6
Classifier: Topic :: Software Development :: Testing
Classifier: License :: OSI Approved :: GNU General Public License v3 (GPLv3)
Requires-Python: >=3.4
License-File: LICENSE.txt
Requires-Dist: SALib
Requires-Dist: CoolProp
